status_ok/__init__.py
status_ok/handle_error.py
status_ok/status.py
status_ok/status_codex.py
status_ok-0.0.4.dist-info/METADATA
status_ok-0.0.4.dist-info/WHEEL
status_ok-0.0.4.dist-info/top_level.txt
status_ok-0.0.4.dist-info/RECORD
